tapas_sumo_coupling/__init__.py
tapas_sumo_coupling/__main__.py
tapas_sumo_coupling/assign.py
tapas_sumo_coupling/common.py
tapas_sumo_coupling/constants.py
tapas_sumo_coupling/database.py
tapas_sumo_coupling/edgemapper.py
tapas_sumo_coupling/emissions.py
tapas_sumo_coupling/get_germany_taz.py
tapas_sumo_coupling/get_motorway_access.py
tapas_sumo_coupling/get_trips.py
tapas_sumo_coupling/import_navteq.py
tapas_sumo_coupling/install_scenario_templates.py
tapas_sumo_coupling/postprocess.py
tapas_sumo_coupling/s2t_miv.py
tapas_sumo_coupling/s2t_pt.py
tapas_sumo_coupling/t2s.py
tapas_sumo_coupling/tsc_main.py
tapas_sumo_coupling-0.23.1.dist-info/licenses/LICENSE
tapas_sumo_coupling-0.23.1.dist-info/METADATA
tapas_sumo_coupling-0.23.1.dist-info/WHEEL
tapas_sumo_coupling-0.23.1.dist-info/entry_points.txt
tapas_sumo_coupling-0.23.1.dist-info/top_level.txt
tapas_sumo_coupling-0.23.1.dist-info/RECORD
