Metadata-Version: 2.4
Name: tapas-sumo-coupling
Version: 0.23.1
License-File: LICENSE
Requires-Dist: rtree
Requires-Dist: pyproj
Requires-Dist: psycopg2
Requires-Dist: pandas
Requires-Dist: sumolib
Dynamic: license-file
